{
  "users": [
    {
      "id": 1,
      "email": "admin@admin.com",
      "password": "123",
      "name": "Admin1",
      "token": "24q3wesrdtfghjiu87y65ref4"
    },
    {
      "id": 2,
      "email": "user@user.com",
      "password": "456",
      "name": "User1",
      "token": "cj48tkjui786rtdfghjiu876"
    },
    {
      "id": 3,
      "email": "service@service.com",
      "password": "789",
      "name": "service1",
      "token": "g59fkj38r4fdkjoir4wut804u"
    },
    {
      "id": 4,
      "email": "siate@siat.com",
      "password": "siat",
      "name": "siat",
      "token": "g59fkj38r4fdkjoir4wut804u"
    },
    {
      "name": "Daniel",
      "email": "danielmcolares@gmail.com",
      "password": "Colares",
      "telefone": "8532731226",
      "genero": "masculino",
      "data_nascimento": "1998-01-14",
      "cidade": "FORTALEZA",
      "estado": "CE",
      "endereco": "RANGEL PESTANA 951",
      "id": 5
    },
    {
      "name": "danilo",
      "email": "danilo@asd.com",
      "password": "123",
      "telefone": "234567890768",
      "genero": "masculino",
      "data_nascimento": "1998-03-12",
      "cidade": "ewadsasfdefre",
      "estado": "qwedasdxaszc",
      "endereco": "qewasdasxz",
      "id": 6
    }
  ],
  "services-provider": [
    {
      "id": 1,
      "email": "serciveces1@service.com",
      "password": "123",
      "name": "Carlos",
      "surname": "Martins",
      "jobs": [
        "encanador",
        "reparador"
      ],
      "description": "Um texto bem grande par você se divertir lendo. Espero que goste.",
      "serviços":[
        {
          "id-cliente": "",
          "status":"",
          "data-do-servico":"",
          "data-de-postagem":"",
          "descricao":"",
          "valor-proposto":"",
          "valor-pago":"",
          "nome-cliente":"",
          "endereco-cliente":""
        }
      ]
      
      
      
    },
    {
      "id": 2,
      "email": "serciveces2@service.com",
      "password": "123",
      "name": "Dimitri",
      "surname": "Kiev",
      "jobs": [
        "encanador"
      ]
    },
    {
      "id": 3,
      "email": "serciveces3@service.com",
      "password": "123",
      "name": "Cristiam",
      "surname": "Suleiman",
      "jobs": [
        "pintor",
        "reparador"
      ]
    },
    {
      "id": 4,
      "email": "serciveces4@service.com",
      "password": "123",
      "name": "Tiago",
      "surname": "Pedroza",
      "jobs": [
        "pintor"
      ]
    },
    {
      "id": 5,
      "email": "serciveces5@service.com",
      "password": "123",
      "name": "Bruno",
      "surname": "Mesquita",
      "jobs": [
        "marceneiro",
        "encanador"
      ]
    },
    {
      "id": 6,
      "email": "serciveces6@service.com",
      "password": "123",
      "name": "Eduardo",
      "surname": "Paiva",
      "jobs": [
        "eletricista"
      ]
    },
    {
      "id": 7,
      "email": "serciveces7@service.com",
      "password": "123",
      "name": "Carlos",
      "surname": "Andrade",
      "jobs": [
        "elettricista",
        "pedreiro"
      ]
    },
    {
      "id": 8,
      "email": "serciveces8@service.com",
      "password": "123",
      "name": "Michel",
      "surname": "Leite",
      "jobs": [
        "encanador",
        "reparador"
      ]
    },
    {
      "id": 9,
      "email": "serciveces9@service.com",
      "password": "123",
      "name": "Matheus",
      "surname": "Carvalho",
      "jobs": [
        "eletricista",
        "reparador",
        "mecanico"
      ]
    },
    {
      "id": 10,
      "email": "serciveces10@service.com",
      "password": "123",
      "name": "Marco",
      "surname": "Tulho",
      "jobs": [
        "eletricista",
        "reparador",
        "encanador",
        "pintor",
        "mecanico"
      ]
    }
  ],
  "comentarios":[
    {
      "id-provedor":"",
      "data-de-postagem":"",
      "comentario":"",
      "estrelas":""
    }
  ]
}